ampyhula/__init__.py
ampyhula/cli.py
ampyhula/files.py
ampyhula/mpreomte_hula.py
ampyhula/progress_bar.py
ampyhula-0.0.4.dist-info/LICENSE
ampyhula-0.0.4.dist-info/METADATA
ampyhula-0.0.4.dist-info/WHEEL
ampyhula-0.0.4.dist-info/entry_points.txt
ampyhula-0.0.4.dist-info/top_level.txt
ampyhula-0.0.4.dist-info/RECORD
