Metadata-Version: 2.1
Name: ampyhula
Version: 0.0.4
Summary: ampyhula is a command line tool to control hula.
Home-page: UNKNOWN
License: UNKNOWN
Requires-Dist: click
